stata_mcp/__init__.py
stata_mcp/cli/__init__.py
stata_mcp/cli/_cli.py
stata_mcp/config/__init__.py
stata_mcp/config/config_manager.py
stata_mcp/core/__init__.py
stata_mcp/core/data_info/__init__.py
stata_mcp/core/data_info/_base.py
stata_mcp/core/data_info/csv.py
stata_mcp/core/data_info/dta.py
stata_mcp/core/stata/__init__.py
stata_mcp/core/stata/stata_controller/__init__.py
stata_mcp/core/stata/stata_controller/controller.py
stata_mcp/core/stata/stata_do/__init__.py
stata_mcp/core/stata/stata_do/do.py
stata_mcp/core/stata/stata_finder/__init__.py
stata_mcp/core/stata/stata_finder/base.py
stata_mcp/core/stata/stata_finder/finder.py
stata_mcp/core/stata/stata_finder/linux.py
stata_mcp/core/stata/stata_finder/macos.py
stata_mcp/core/stata/stata_finder/windows.py
stata_mcp/server/__init__.py
stata_mcp/server/main.py
stata_mcp/server/prompts/__init__.py
stata_mcp/server/prompts/core_prompts.py
stata_mcp/server/tools/__init__.py
stata_mcp/server/tools/core_tools.py
stata_mcp/server/tools/file_tools.py
stata_mcp/server/tools/stata_tools.py
stata_mcp/utils/__init__.py
stata_mcp/utils/usable.py
stata_mcp/utils/Installer/__init__.py
stata_mcp/utils/Installer/installer.py
stata_mcp/utils/Prompt/__init__.py
stata_mcp/utils/Prompt/string.py
aigroup_stata_mcp-1.0.9.dist-info/METADATA
aigroup_stata_mcp-1.0.9.dist-info/WHEEL
aigroup_stata_mcp-1.0.9.dist-info/entry_points.txt
aigroup_stata_mcp-1.0.9.dist-info/licenses/LICENSE
aigroup_stata_mcp-1.0.9.dist-info/RECORD
