Metadata-Version: 2.4
Name: aigroup-stata-mcp
Version: 1.0.9
Summary: A Stata integration server based on Model Context Protocol (MCP) that allows AI assistants to execute Stata scripts, fetch data information, and run statistical analysis.
Author-email: jackdark425 <jackdark425@gmail.com>
License: MIT
License-File: LICENSE
Keywords: ai,data-analysis,mcp,model-context-protocol,stata,statistics
Classifier: Development Status :: 4 - Beta
Classifier: Intended Audience :: Science/Research
Classifier: License :: OSI Approved :: MIT License
Classifier: Operating System :: OS Independent
Classifier: Programming Language :: Python :: 3
Classifier: Programming Language :: Python :: 3.11
Classifier: Programming Language :: Python :: 3.12
Classifier: Programming Language :: Python :: 3.13
Classifier: Topic :: Scientific/Engineering
Classifier: Topic :: Software Development :: Libraries :: Python Modules
Requires-Python: >=3.11
Requires-Dist: mcp[cli]>=1.21.0
Requires-Dist: numpy>=1.24.0
Requires-Dist: openpyxl>=3.1.5
Requires-Dist: pandas>=2.3.0
Requires-Dist: pathvalidate>=3.3.1
Requires-Dist: pexpect>=4.9.0
Requires-Dist: pydantic>=2.0.0
Requires-Dist: python-dotenv>=1.1.1
Requires-Dist: requests>=2.31.0
Provides-Extra: config
Requires-Dist: tomli-w>=1.0.0; extra == 'config'
Requires-Dist: tomli>=2.0.1; (python_version < '3.11') and extra == 'config'
